LICENSE
MANIFEST.in
README.rst
setup.py
pyllage/__init__.py
pyllage/http.py
pyllage/parser.py
pyllage/selectors.py
pyllage/utils.py
pyllage.egg-info/PKG-INFO
pyllage.egg-info/SOURCES.txt
pyllage.egg-info/dependency_links.txt
pyllage.egg-info/not-zip-safe
pyllage.egg-info/top_level.txt
pyllage/tests/__init__.py
pyllage/tests/test_http.py
pyllage/tests/test_parser.py
pyllage/tests/test_selectors.py
pyllage/tests/test_utils.py