Metadata-Version: 1.0
Name: pyllage
Version: 0.1.2
Summary: A web scraping tool in Python 3
Home-page: https://github.com/barisumog/pyllage
Author: barisumog
Author-email: barisumog@gmail.com
License: GPLv3
Keywords: web scraper scraping
Platform: UNKNOWN
